tencentcloud/__init__.py
tencentcloud/casb/__init__.py
tencentcloud/casb/v20200507/__init__.py
tencentcloud/casb/v20200507/casb_client.py
tencentcloud/casb/v20200507/errorcodes.py
tencentcloud/casb/v20200507/models.py
tencentcloud_sdk_python_casb-3.0.1033.dist-info/METADATA
tencentcloud_sdk_python_casb-3.0.1033.dist-info/WHEEL
tencentcloud_sdk_python_casb-3.0.1033.dist-info/top_level.txt
tencentcloud_sdk_python_casb-3.0.1033.dist-info/RECORD
